{
    "bucketName": "retail9765318dece64d78837883e645fe092b",
    "authPolicyName": "s3_amplify_473d96f7",
    "unauthPolicyName": "s3_amplify_473d96f7",
    "authRoleName": {
        "Ref": "AuthRoleName"
    },
    "unauthRoleName": {
        "Ref": "UnauthRoleName"
    },
    "selectedGuestPermissions": [
        "s3:GetObject",
        "s3:ListBucket"
    ],
    "selectedAuthenticatedPermissions": [
        "s3:PutObject",
        "s3:GetObject",
        "s3:ListBucket"
    ],
    "s3PermissionsAuthenticatedPublic": "s3:PutObject,s3:GetObject",
    "s3PublicPolicy": "Public_policy_52895a72",
    "s3PermissionsAuthenticatedUploads": "s3:PutObject",
    "s3UploadsPolicy": "Uploads_policy_52895a72",
    "s3PermissionsAuthenticatedProtected": "s3:PutObject,s3:GetObject",
    "s3ProtectedPolicy": "Protected_policy_76e9ed8f",
    "s3PermissionsAuthenticatedPrivate": "s3:PutObject,s3:GetObject",
    "s3PrivatePolicy": "Private_policy_76e9ed8f",
    "AuthenticatedAllowList": "ALLOW",
    "s3ReadPolicy": "read_policy_52895a72",
    "s3PermissionsGuestPublic": "s3:GetObject",
    "s3PermissionsGuestUploads": "DISALLOW",
    "GuestAllowList": "ALLOW",
    "triggerFunction": "S3Triggerf397a608"
}